common/.DS_Store
common/__init__.py
common/common_async/__init__.py
common/common_async/async_error_tool.py
common/common_async/async_time_tool.py
common/draw_tool.py
common/error_tool.py
common/func_tool.py
common/parse_tool.py
common/time_tool.py
xv521_common_tool_kit-0.1.3.dist-info/METADATA
xv521_common_tool_kit-0.1.3.dist-info/WHEEL
xv521_common_tool_kit-0.1.3.dist-info/RECORD
